yessql/__init__.py
yessql/__main__.py
yessql/aiomysql.py
yessql/config.py
yessql/logger.py
yessql/postgres.py
yessql/utils.py
yessql/aiopostgres/__init__.py
yessql/aiopostgres/client.py
yessql/aiopostgres/params.py
yessql-0.1.0.dist-info/LICENSE
yessql-0.1.0.dist-info/METADATA
yessql-0.1.0.dist-info/WHEEL
yessql-0.1.0.dist-info/top_level.txt
yessql-0.1.0.dist-info/RECORD
